odoo/addons/partner_multi_relation_function/README.rst
odoo/addons/partner_multi_relation_function/__init__.py
odoo/addons/partner_multi_relation_function/__manifest__.py
odoo/addons/partner_multi_relation_function/demo/res_partner_demo.xml
odoo/addons/partner_multi_relation_function/demo/res_partner_relation_demo.xml
odoo/addons/partner_multi_relation_function/demo/res_partner_relation_type_demo.xml
odoo/addons/partner_multi_relation_function/i18n/it.po
odoo/addons/partner_multi_relation_function/i18n/partner_multi_relation_function.pot
odoo/addons/partner_multi_relation_function/models/__init__.py
odoo/addons/partner_multi_relation_function/models/res_partner.py
odoo/addons/partner_multi_relation_function/models/res_partner_relation.py
odoo/addons/partner_multi_relation_function/models/res_partner_relation_all.py
odoo/addons/partner_multi_relation_function/models/res_partner_relation_type.py
odoo/addons/partner_multi_relation_function/models/res_partner_relation_type_selection.py
odoo/addons/partner_multi_relation_function/readme/CONTRIBUTORS.rst
odoo/addons/partner_multi_relation_function/readme/DESCRIPTION.rst
odoo/addons/partner_multi_relation_function/readme/USAGE.rst
odoo/addons/partner_multi_relation_function/static/description/icon.png
odoo/addons/partner_multi_relation_function/static/description/index.html
odoo/addons/partner_multi_relation_function/tests/__init__.py
odoo/addons/partner_multi_relation_function/tests/test_partner_search.py
odoo/addons/partner_multi_relation_function/views/res_partner_relation_all_views.xml
odoo/addons/partner_multi_relation_function/views/res_partner_relation_type_views.xml
odoo/addons/partner_multi_relation_function/views/res_partner_views.xml
odoo_addon_partner_multi_relation_function-16.0.1.1.0.2.dist-info/METADATA
odoo_addon_partner_multi_relation_function-16.0.1.1.0.2.dist-info/WHEEL
odoo_addon_partner_multi_relation_function-16.0.1.1.0.2.dist-info/top_level.txt
odoo_addon_partner_multi_relation_function-16.0.1.1.0.2.dist-info/RECORD
