Metadata-Version: 2.1
Name: odoo-addon-partner_multi_relation_function
Version: 16.0.1.1.0.2
Summary: Partner Relation Functions
Home-page: https://github.com/OCA/partner-contact
Author: Therp BV,Odoo Community Association (OCA)
Author-email: support@odoo-community.org
License: AGPL-3
Classifier: Programming Language :: Python
Classifier: Framework :: Odoo
Classifier: Framework :: Odoo :: 16.0
Classifier: License :: OSI Approved :: GNU Affero General Public License v3
Requires-Python: >=3.10
Requires-Dist: odoo-addon-partner-multi-relation<16.1dev,>=16.0dev
Requires-Dist: odoo<16.1dev,>=16.0a
